SqliteDocumentation/README.md
SqliteDocumentation/__init__.py
SqliteDocumentation/__main__.py
SqliteDocumentation/file.epub
SqliteDocumentation/index.html
SqliteDocumentation/css/__init__.py
SqliteDocumentation/css/annotations.css
SqliteDocumentation/css/main.css
SqliteDocumentation/css/normalize.css
SqliteDocumentation/css/popup.css
SqliteDocumentation/font/__init__.py
SqliteDocumentation/font/fontello.eot
SqliteDocumentation/font/fontello.svg
SqliteDocumentation/font/fontello.ttf
SqliteDocumentation/font/fontello.woff
SqliteDocumentation/img/__init__.py
SqliteDocumentation/img/annotator-glyph-sprite.png
SqliteDocumentation/img/annotator-icon-sprite.png
SqliteDocumentation/img/apple-touch-icon.png
SqliteDocumentation/img/cancelfullscreen.png
SqliteDocumentation/img/close.png
SqliteDocumentation/img/fullscreen.png
SqliteDocumentation/img/loader.gif
SqliteDocumentation/img/menu-icon.png
SqliteDocumentation/img/save.png
SqliteDocumentation/img/saved.png
SqliteDocumentation/img/settings-s.png
SqliteDocumentation/img/settings.png
SqliteDocumentation/img/star.png
SqliteDocumentation/js/__init__.py
SqliteDocumentation/js/epub.js
SqliteDocumentation/js/epub.min.js
SqliteDocumentation/js/epub.min.map
SqliteDocumentation/js/hooks.min.js
SqliteDocumentation/js/hooks.min.map
SqliteDocumentation/js/reader.js
SqliteDocumentation/js/reader.js.map
SqliteDocumentation/js/reader.min.js
SqliteDocumentation/js/reader.min.map
SqliteDocumentation/js/hooks/__init__.py
SqliteDocumentation/js/hooks/extensions/__init__.py
SqliteDocumentation/js/hooks/extensions/highlight.js
SqliteDocumentation/js/libs/__init__.py
SqliteDocumentation/js/libs/jquery.min.js
SqliteDocumentation/js/libs/localforage.min.js
SqliteDocumentation/js/libs/screenfull.js
SqliteDocumentation/js/libs/screenfull.min.js
SqliteDocumentation/js/libs/zip.min.js
SqliteDocumentation/js/plugins/__init__.py
SqliteDocumentation/js/plugins/hypothesis.js
SqliteDocumentation/js/plugins/search.js
sqlite_documentation-2024.3.2.0.dist-info/METADATA
sqlite_documentation-2024.3.2.0.dist-info/WHEEL
sqlite_documentation-2024.3.2.0.dist-info/entry_points.txt
sqlite_documentation-2024.3.2.0.dist-info/top_level.txt
sqlite_documentation-2024.3.2.0.dist-info/RECORD
